myFirstLibrary/__init__.py
myFirstLibrary/math_operations.py
myFirstLibrary-1.0.0.dist-info/METADATA
myFirstLibrary-1.0.0.dist-info/WHEEL
myFirstLibrary-1.0.0.dist-info/top_level.txt
myFirstLibrary-1.0.0.dist-info/RECORD
