Metadata-Version: 2.1
Name: myFirstLibrary
Version: 1.0.0
Summary: A library for basic math operations
Author: test user
